Workbook

Sheet Start Here
A1: PakFreight Data Detective — Week 2 Activity
A2: Data Warehousing & BI · Week 2 — DW Lifecycle & Architecture. PakFreight has three shipment systems (Marine, Rail, Road). Every department reports a different total tonnage. Your team will find out why, fix it in a staging area, and prove the one true number.
A4: How to work
A5: • | B5: Work in teams of 3. Name one person each: Operations, Finance, Sales (needed in Task 2).
A6: • | B6: Do the tasks in order — each tab is named T1, T2 … The minutes are a guide; your teacher will call time.
A7: • | B7: Only type in YELLOW cells. GREY cells are raw data as received — never edit them (that is the point of staging!).
A8: • | B8: Task 4 checks your work automatically: every ✘ means something in Task 3 is still wrong.
A9: • | B9: Task 8 (draw Inmon vs Kimball) is done on paper — see the slide 'Your Turn: Draw Both Architectures'.
A10: • | B10: Save the file as Team_<number>.xlsx and submit it with a photo of your drawing.
A12: Plan
A13: # | B13: Task | C13: Tab | D13: 60-min class | E13: 45-min class | F13: Concept from the slides
A14: 0 | B14: Teacher intro: the '3 different totals' problem | C14: — | D14: 5 | E14: 3 | F14: Slide 17 stovepipes
A15: 1 | B15: Data Detective — log every problem in the raw files | C15: T1 Detective | D15: 8 | E15: 6 | F15: Staging: profile before load
A16: 2 | B16: Stovepipe Game — each department computes its own total | C16: T2 Stovepipes | D16: 7 | E16: 5 | F16: Independent vs dependent marts
A17: 3 | B17: Clean the 3 files in staging with formulas | C17: T3a / T3b / T3c | D17: 15 | E17: 12 | F17: Staging transformations
A18: 4 | B18: Reconcile — prove 34 rows and 578,650 kg | C18: T4 Reconcile | D18: 3 | E18: 3 | F18: Validate before you trust
A19: 5 | B19: Trace the lineage of one number | C19: T5 Lineage | D19: 5 | E19: 0 | F19: Lineage (slide 29) — homework in 45-min version
A20: 6 | B20: Kimball Bus Matrix | C20: T6 Bus Matrix | D20: 7 | E20: 6 | F20: Conformed dimensions
A21: 7 | B21: Inmon or Kimball? — 10 scenarios | C21: T7 Inmon or Kimball | D21: 5 | E21: 5 | F21: Top-down vs bottom-up
A22: 8 | B22: Draw both architectures (paper) | C22: Slide 20c | D22: 5 | E22: 5 | F22: Inmon CIF vs Kimball bus
B23: Total minutes | D23: =SUM(D14:D22) -> 60 | E23: =SUM(E14:E22) -> 45
A25: Colour legend
B26: You type here
B27: Raw data — do not edit
B28: ✔ check passed
B29: ✘ check failed — go back and fix
A31: The data contract (target schema)
A32: Column | B32: Type | C32: Rule | D32: Example
A33: ShipmentID | B33: Text | C33: Not blank · unique · prefix MR- / RL- / RD- | D33: RL-45012
A34: ShipDate | B34: Date | C34: Real date (dd-mmm-yyyy) | D34: 03-Feb-2026
A35: Origin | B35: Text
A36: Destination | B36: Text
A37: WeightKG | B37: Number | C37: > 0 · kilograms only | D37: 32,500
A38: CostPKR | B38: Number | C38: > 0 | D38: 285,000
A39: Status | B39: Text | C39: Exactly one of: Delivered · In Transit · Delayed | D39: Delivered
A40: SourceSystem | B40: Text | C40: Marine · Rail · Road (audit column) | D40: Rail

Sheet Marine_Raw
A1: Shipment_ID | B1: Ship_Date | C1: Origin_Port | D1: Dest_Port | E1: Weight_KG | F1: Cost_PKR | G1: Status
A2: MR-1001 | B2: 01/02/2026 | C2: Karachi Port | D2: Lahore Dry Port | E2: 18000 | F2: 142000 | G2: DELIVERED
A3: MR-1002 | B3: 02/02/2026 | C3: Port Qasim | D3: Faisalabad Dry Port | E3: 22500 | F3: 171000 | G3: DELIVERED
A4: MR-1003 | B4: 03/02/2026 | C4: Karachi Port | D4: Lahore Dry Port | E4: 15000 | F4: 119000 | G4: IN TRANSIT
A5: MR-1004 | B5: 04/02/2026 | C5: Gwadar Port | D5: Quetta | E5: 20000 | F5: 188000 | G5: DELIVERED
A6: MR-1005 | B6: 05/02/2026 | C6: Port Qasim | D6: Multan | E6: 16500 | F6: 128000 | G6: DELIVERED
A7: MR-1006 | B7: 06/02/2026 | C7: Karachi Port | D7: Sialkot Dry Port | E7: 19000 | F7: 154000 | G7: DELAYED
A8: MR-1007 | B8: 07/02/2026 | C8: Port Qasim | D8: Lahore Dry Port | E8: 14000 | F8: 109000 | G8: DELIVERED
A9: MR-1008 | B9: 09/02/2026 | C9: Karachi Port | D9: Peshawar | E9: 21000 | F9: 197000 | G9: IN TRANSIT
A10: MR-1009 | B10: 10/02/2026 | C10: Gwadar Port | D10: Karachi Cantt | E10: 17500 | F10: 98000 | G10: DELIVERED
A11: MR-1010 | B11: 11/02/2026 | C11: Port Qasim | D11: Islamabad Dry Port | E11: 15500 | F11: 139000 | G11: DELIVERED
A12: MR-1011 | B12: 12/02/2026 | C12: Karachi Port | D12: Hyderabad | E12: 13500 | F12: 61000 | G12: IN TRANSIT
A13: MR-1012 | B13: 13/02/2026 | C13: Port Qasim | D13: Lahore Dry Port | E13: 14000 | F13: 112000 | G13: DELIVERED

Sheet Rail_Raw
A1: Pakistan Railways Freight — Consignment Register
A2: Period: February 2026 | Weights in TONS
A3: Consignment No | B3: Dispatch Date | C3: From Station | D3: To Station | E3: Weight (Tons) | F3: Freight Charges (PKR) | G3: Status
A4: 45012 | B4: 46056 | C4: Karachi Cantt | D4: Lahore | E4: 32.5 | F4: 285000 | G4: Delivered
A5: 45013 | B5: 46056 | C5: Karachi Cantt | D5: Rawalpindi | E5: 28.75 | F5: 301000 | G5: delivered
A6: 45014 | B6: 46057 | C6: Pipri Marshalling Yard | D6: Faisalabad | E6: 30 | F6: 262000 | G6: In transit
A7: 45015 | B7: 46058 | C7: Karachi Cantt | D7: Multan | E7: 26.5 | F7: 198000 | G7: Delivered
A8: 45016 | B8: 46059 | C8: Pipri Marshalling Yard | D8: Lahore | E8: 31.25 | F8: 276000 | G8: DELAYED
A9: 45017 | B9: 46060 | C9: Karachi Cantt | D9: Peshawar Cantt | E9: 29 | F9: 334000 | G9: Delivered
A10: 45018 | B10: 46062 | C10: Pipri Marshalling Yard | D10: Rawalpindi | E10: 27.5 | F10: 289000 | G10: delayed
A11: 45019 | B11: 46063 | C11: Karachi Cantt | D11: Lahore | E11: 33 | F11: 291000 | G11: Delivered
A12: 45020 | B12: 46064 | C12: Karachi Cantt | D12: Sukkur | E12: 28.25 | F12: 142000 | G12: in Transit
A13: 45021 | B13: 46065 | C13: Pipri Marshalling Yard | D13: Multan | E13: 28.5 | F13: 207000 | G13: delivered

Sheet Road_Raw
A1: trip_id | B1: trip_date | C1: from_city | D1: to_city | E1: weight_kg | F1: cost_pkr | G1: status
A2: rd-501 | B2: 2026-02-02 | C2: Lahore | D2: Islamabad | E2: 6500 | F2: 58000 | G2: delivered
A3: rd-502 | B3: 2026-02-02 | C3: Karachi | D3: Hyderabad | E3: 7200 | F3: 41000 | G3: delivered
A4: rd-503 | B4: 2026-02-03 | C4: Lahore | D4: Faisalabad | E4: 5800 | F4: 32000 | G4: in transit
A5: rd-504 | B5: 2026-02-04 | C5: Multan | D5: Lahore | E5: 6900 | F5: 61000 | G5: delivered
A6: rd-505 | B6: 2026-02-05 | C6: Islamabad | D6: Peshawar | E6: 6100 | F6: 47000 | G6: delivered
A7: rd-505 | B7: 2026-02-05 | C7: Islamabad | D7: Peshawar | E7: 6100 | F7: 47000 | G7: delivered
A8: rd-506 | B8: 2026-02-06 | C8: Karachi | D8: Sukkur | E8: 7400 | F8: 83000 | G8: delayed
A9: rd-507 | B9: 2026-02-07 | C9: Lahore | D9: Sialkot | E9: 5900 | F9: 39000 | G9: delivered
A10: rd-508 | B10: 2026-02-09 | C10: Quetta | D10: Karachi | E10: 6600 | F10: 92000 | G10: in transit
A11: rd-509 | B11: 2026-02-10 | C11: Faisalabad | D11: Multan | E11: 6200 | F11: 44000 | G11: delivered
A12: rd-510 | B12: 2026-02-11 | C12: Lahore | D12: Gujranwala | E12: 7000 | F12: 27000 | G12: delivered
A13: rd-511 | B13: 2026-02-12 | C13: Karachi | D13: Hyderabad | E13: 5500 | F13: 36000 | G13: in transit
A14: rd-512 | B14: 2026-02-13 | C14: Rawalpindi | D14: Abbottabad | E14: 5800 | F14: 45000 | G14: delivered
A16: TOTAL | E16: 83000 | F16: 652000

Sheet T1 Detective
A1: Task 1 · Data Detective (8 min)
A2: Open Marine_Raw, Rail_Raw and Road_Raw. Find at least 10 problems that would break or silently corrupt a warehouse load. For each one say what would go wrong and in which tier you would fix it (Source / Staging / Storage / Presentation). The first row is an example.
A4: # | B4: Source file | C4: Where (column / row) | D4: Problem you found | E4: What goes wrong if loaded as-is? | F4: Fix in which tier? | G4: How would you fix it?
A5: 1 | B5: Marine | C5: Ship_Date (all rows) | D5: Dates are text in dd/mm/yyyy | E5: A US-locale tool reads 03/02 as 2 March; 13/02/2026 becomes an error | F5: Staging | G5: Convert to a real date using the UK locale
A6: 2 | B6: Rail | C6: Header Metadata / Weight (Tons) | D6: Unit Mismatch: Rail measures weight in metric tons (e.g., 32.50), while Marine and Road measure weight in kg. | E6: Reports will treat 32.50 kg instead of 32,500 kg, undercounting total rail weight by 1,000x (leading to Finance's wrong answer). | F6: Staging (ETL) | G6: Multiply the Weight (Tons) column by 1,000 using a formula to convert all values to kilograms.
A7: 3 | B7: Road | C7: Row 18 / TOTAL | D7: Non-Data Row: A summary TOTAL row (83,000 weight and 652,000 cost) is embedded at the bottom of the raw file. | E7: Summing the column double-counts all road records, inflating total freight weight by 83 tonnes (leading to Operations' wrong answer). | F7: Staging (ETL) | G7: Filter out and drop rows where trip_id equals "TOTAL" or where trip_id is not a valid transaction ID.
A8: 4 | B8: Road | C8: Rows 6 & 7 / rd-505 | D8: Duplicate Row: Record rd-505 (Islamabad to Peshawar, 6,100 kg) is listed twice with identical data. | E8: Artificially inflates total shipment counts and overcounts weight by 6,100 kg (leading to Sales' wrong answer). | F8: Staging (ETL) | G8: Apply a deduplication transformation or drop duplicate rows based on trip_id.
A9: 5 | B9: Road | C9: Row 16 | D9: Blank Row: An entirely empty row exists between rd-512 and the TOTAL row. | E9: Causes null/missing value errors, breaks row counts, or introduces unwanted blank entries in reporting visualizations. | F9: Staging (ETL) | G9: Filter out and drop completely empty rows before loading data into staging tables.
A10: 6 | B10: Marine vs Road vs Rail | C10: Ship_Date / Dispatch Date / trip_date | D10: Inconsistent Date Formats: Marine uses DD/MM/YYYY (01/02/2026), Rail uses DD-MMM-YYYY (03-Feb-2026), and Road uses YYYY-MM-DD (2026-02-02). | E10: Date filters, monthly aggregations, and date dimensions across different modes will fail or produce conversion errors. | F10: Staging (ETL) | G10: Cast and standardize all date columns into standard ANSI date format (YYYY-MM-DD).
A11: 7 | B11: Marine vs Road vs Rail | C11: Status | D11: Text Casing & Spacing Issues: Status values contain mixed casing (DELIVERED, Delivered, delivered, in Transit) and leading/trailing whitespace. | E11: BI slicers and group-by aggregations will treat "DELIVERED" and "delivered" as two separate status categories. | F11: Staging (ETL) | G11: Standardize casing using =PROPER(TRIM(Status)) or =UPPER(TRIM(Status)) across all files.
A12: 8 | B12: Marine vs Road vs Rail | C12: Primary Key Identifiers | D12: Inconsistent Key Formatting: Identifiers use completely different casing and syntax structures (MR-1001 vs numeric 45012 vs lowercase rd-501). | E12: Impairs direct data cross-referencing, breaks automated validation checks, and causes inconsistent naming conventions in data models. | F12: Staging (ETL) | G12: Standardize primary key formats to uppercase strings (e.g., MR-1001, RL-45012, RD-501).
A13: 9 | B13: Rail | C13: Rows 1 & 2 | D13: Metadata in Header Rows: Header text ("Pakistan Railways Freight...", "Period: February 2026...") is present above the column headers. | E13: Direct automated ingestion scripts will mistake administrative descriptive text for data header columns. | F13: Ingestion (Source / ETL) | G13: Configure file load options to skip the top two header rows during ingestion.
A14: 10 | B14: Marine vs Road vs Rail | C14: Column Headers | D14: Inconsistent Header Naming: Equivalent attributes have different names (e.g., Shipment_ID vs Consignment No vs trip_id; Origin_Port vs From Station vs from_city). | E14: Prevents direct UNION ALL staging operations without manual column mapping. | F14: Staging (ETL) | G14: Rename header columns to a standard schema across all 3 staging tables (e.g., Shipment_ID, Origin, Destination, Weight_KG, Cost_PKR, Status).
A15: 11 | B15: Marine vs Road vs Rail | C15: City / Location Names | D15: Unconformed Location Granularity: Locations mix specific facility names with generic city names (e.g., Karachi Port, Karachi Cantt, Pipri Marshalling Yard, and Karachi). | E15: Regional reporting by city will fragment Karachi into 4 different location slices instead of aggregating them cleanly under one conformed Location dimension. | F15: Dimensional Modeling / Staging | G15: Map raw location strings to a conformed Location Dimension containing standard City and Facility_Name attributes.
A16: 12
D18: Issues found: | E18: =COUNTA(D5:D16) -> 11

Sheet T2 Stovepipes
A1: Task 2 · The Stovepipe Game (7 min)
A2: Each team member plays one department that built its OWN mini-warehouse with its OWN rules. Write a formula in the yellow cell that adds up the raw sheets following ONLY your department's rule. Then compare.
A4: Department | B4: Their (flawed) rule | C4: Your formula → total kg | D4: Tonnes | E4: Difference from truth (t) | F4: Hint
A5: Operations | B5: Removed the duplicate rd-505 ✔ but forgot to remove the TOTAL row ✘. Rail converted to kg ✔. | C5: =206500 + 295250 + (166000 - 6100) -> 661650 | D5: =IF(C5="","",C5/1000) -> 661.65 | E5: =IF(C5="","",D5-$D$9) -> 83 | F5: SUM the whole Road column (TOTAL included) then subtract the duplicate row
A6: Finance | B6: Cleaned Road correctly ✔ but loaded Rail tonnes as if they were kg ✘. | C6: =206500 + 295.25 + 76900 -> 283695.25 | D6: =IF(C6="","",C6/1000) -> 283.69525 | E6: =IF(C6="","",D6-$D$9) -> -294.95475 | F6: Don't multiply Rail by 1000
A7: Sales | B7: Removed the TOTAL row ✔ but kept the duplicate trip ✘. Rail converted to kg ✔. | C7: =206500 + 295250 + 8300 -> 510050 | D7: =IF(C7="","",C7/1000) -> 510.05 | E7: =IF(C7="","",D7-$D$9) -> -68.6 | F7: Road rows 2–14 include the duplicate
A9: Official truth | B9: One staging area, one set of rules (dependent / conformed marts) | C9: 578650 | D9: =C9/1000 -> 578.65
A11: Discuss (write one line each)
A12: Q1. All three teams were honest. Why are their numbers different?
A13: Each department worked in isolated data silos, applying different manual cleaning rules to raw, unvalidated source files without a central single source of truth.
A14: Q2. Which department's mistake is the most dangerous, and why?
A15: Finance's mistake is the most dangerous because ignoring unit headers caused a massive under-reporting of 294.95 tonnes 51% error margin, leading to severe financial misstatements.
A16: Q3. What architecture change makes all three report the same number?
A17: Implementing a centralized Data Warehouse with a single, automated staging pipeline (Single Source of Truth) feeding all departmental reports
A18: Q4. Which role should decide the official definition (e.g. what counts as one shipment)?
A19: A Data Governance Manager (or Lead Business Analyst/Data Steward) in collaboration with department leads should establish and enforce unified business definitions.

Sheet T3a Marine_Stg
A1: Task 3a · Stage the Marine file
A2: Write one formula in the first yellow cell of each column, then drag it down. Columns that are already filled are simple copies.
A3: RAW — copied exactly as received (grey, don't edit) | H3: STAGED — contract columns (your formulas in yellow)
A4: Shipment_ID | B4: Ship_Date | C4: Origin_Port | D4: Dest_Port | E4: Weight_KG | F4: Cost_PKR | G4: Status | H4: ShipmentID | I4: ShipDate | J4: Origin | K4: Destination | L4: WeightKG | M4: CostPKR | N4: Status | O4: SourceSystem | R4: Hints
A5: MR-1001 | B5: 01/02/2026 | C5: Karachi Port | D5: Lahore Dry Port | E5: 18000 | F5: 142000 | G5: DELIVERED | H5: =A5 -> MR-1001 | I5: =DATE(RIGHT(B5,4), MID(B5,4,2), LEFT(B5,2)) -> 46054 | J5: =C5 -> Karachi Port | K5: =D5 -> Lahore Dry Port | L5: =E5 -> 18000 | M5: =F5 -> 142000 | N5: =PROPER(TRIM(G5)) -> Delivered | O5: ="Marine" -> Marine | R5: ShipDate: B is TEXT like 03/02/2026 = 3 February. Pull day, month, year with LEFT, MID, RIGHT and build a date with DATE(year, month, day).
A6: MR-1002 | B6: 02/02/2026 | C6: Port Qasim | D6: Faisalabad Dry Port | E6: 22500 | F6: 171000 | G6: DELIVERED | H6: =A6 -> MR-1002 | I6: =DATE(RIGHT(B6,4), MID(B6,4,2), LEFT(B6,2)) -> 46055 | J6: =C6 -> Port Qasim | K6: =D6 -> Faisalabad Dry Port | L6: =E6 -> 22500 | M6: =F6 -> 171000 | N6: =PROPER(TRIM(G6)) -> Delivered | O6: ="Marine" -> Marine | R6: TRAP CHECK: MR-1003 must show 03-Feb-2026 (not 02-Mar) and MR-1012 must show 13-Feb-2026 (not an error).
A7: MR-1003 | B7: 03/02/2026 | C7: Karachi Port | D7: Lahore Dry Port | E7: 15000 | F7: 119000 | G7: IN TRANSIT | H7: =A7 -> MR-1003 | I7: =DATE(RIGHT(B7,4), MID(B7,4,2), LEFT(B7,2)) -> 46056 | J7: =C7 -> Karachi Port | K7: =D7 -> Lahore Dry Port | L7: =E7 -> 15000 | M7: =F7 -> 119000 | N7: =PROPER(TRIM(G7)) -> In Transit | O7: ="Marine" -> Marine | R7: Status: remove hidden spaces first, then fix the case. Look up TRIM and PROPER.
A8: MR-1004 | B8: 04/02/2026 | C8: Gwadar Port | D8: Quetta | E8: 20000 | F8: 188000 | G8: DELIVERED | H8: =A8 -> MR-1004 | I8: =DATE(RIGHT(B8,4), MID(B8,4,2), LEFT(B8,2)) -> 46057 | J8: =C8 -> Gwadar Port | K8: =D8 -> Quetta | L8: =E8 -> 20000 | M8: =F8 -> 188000 | N8: =PROPER(TRIM(G8)) -> Delivered | O8: ="Marine" -> Marine | R8: SourceSystem: every row gets the same text — this is your audit column.
A9: MR-1005 | B9: 05/02/2026 | C9: Port Qasim | D9: Multan | E9: 16500 | F9: 128000 | G9: DELIVERED | H9: =A9 -> MR-1005 | I9: =DATE(RIGHT(B9,4), MID(B9,4,2), LEFT(B9,2)) -> 46058 | J9: =C9 -> Port Qasim | K9: =D9 -> Multan | L9: =E9 -> 16500 | M9: =F9 -> 128000 | N9: =PROPER(TRIM(G9)) -> Delivered | O9: ="Marine" -> Marine
A10: MR-1006 | B10: 06/02/2026 | C10: Karachi Port | D10: Sialkot Dry Port | E10: 19000 | F10: 154000 | G10: DELAYED | H10: =A10 -> MR-1006 | I10: =DATE(RIGHT(B10,4), MID(B10,4,2), LEFT(B10,2)) -> 46059 | J10: =C10 -> Karachi Port | K10: =D10 -> Sialkot Dry Port | L10: =E10 -> 19000 | M10: =F10 -> 154000 | N10: =PROPER(TRIM(G10)) -> Delayed | O10: ="Marine" -> Marine
A11: MR-1007 | B11: 07/02/2026 | C11: Port Qasim | D11: Lahore Dry Port | E11: 14000 | F11: 109000 | G11: DELIVERED | H11: =A11 -> MR-1007 | I11: =DATE(RIGHT(B11,4), MID(B11,4,2), LEFT(B11,2)) -> 46060 | J11: =C11 -> Port Qasim | K11: =D11 -> Lahore Dry Port | L11: =E11 -> 14000 | M11: =F11 -> 109000 | N11: =PROPER(TRIM(G11)) -> Delivered | O11: ="Marine" -> Marine
A12: MR-1008 | B12: 09/02/2026 | C12: Karachi Port | D12: Peshawar | E12: 21000 | F12: 197000 | G12: IN TRANSIT | H12: =A12 -> MR-1008 | I12: =DATE(RIGHT(B12,4), MID(B12,4,2), LEFT(B12,2)) -> 46062 | J12: =C12 -> Karachi Port | K12: =D12 -> Peshawar | L12: =E12 -> 21000 | M12: =F12 -> 197000 | N12: =PROPER(TRIM(G12)) -> In Transit | O12: ="Marine" -> Marine
A13: MR-1009 | B13: 10/02/2026 | C13: Gwadar Port | D13: Karachi Cantt | E13: 17500 | F13: 98000 | G13: DELIVERED | H13: =A13 -> MR-1009 | I13: =DATE(RIGHT(B13,4), MID(B13,4,2), LEFT(B13,2)) -> 46063 | J13: =C13 -> Gwadar Port | K13: =D13 -> Karachi Cantt | L13: =E13 -> 17500 | M13: =F13 -> 98000 | N13: =PROPER(TRIM(G13)) -> Delivered | O13: ="Marine" -> Marine
A14: MR-1010 | B14: 11/02/2026 | C14: Port Qasim | D14: Islamabad Dry Port | E14: 15500 | F14: 139000 | G14: DELIVERED | H14: =A14 -> MR-1010 | I14: =DATE(RIGHT(B14,4), MID(B14,4,2), LEFT(B14,2)) -> 46064 | J14: =C14 -> Port Qasim | K14: =D14 -> Islamabad Dry Port | L14: =E14 -> 15500 | M14: =F14 -> 139000 | N14: =PROPER(TRIM(G14)) -> Delivered | O14: ="Marine" -> Marine
A15: MR-1011 | B15: 12/02/2026 | C15: Karachi Port | D15: Hyderabad | E15: 13500 | F15: 61000 | G15: IN TRANSIT | H15: =A15 -> MR-1011 | I15: =DATE(RIGHT(B15,4), MID(B15,4,2), LEFT(B15,2)) -> 46065 | J15: =C15 -> Karachi Port | K15: =D15 -> Hyderabad | L15: =E15 -> 13500 | M15: =F15 -> 61000 | N15: =PROPER(TRIM(G15)) -> In Transit | O15: ="Marine" -> Marine
A16: MR-1012 | B16: 13/02/2026 | C16: Port Qasim | D16: Lahore Dry Port | E16: 14000 | F16: 112000 | G16: DELIVERED | H16: =A16 -> MR-1012 | I16: =DATE(RIGHT(B16,4), MID(B16,4,2), LEFT(B16,2)) -> 46066 | J16: =C16 -> Port Qasim | K16: =D16 -> Lahore Dry Port | L16: =E16 -> 14000 | M16: =F16 -> 112000 | N16: =PROPER(TRIM(G16)) -> Delivered | O16: ="Marine" -> Marine

Sheet T3b Rail_Stg
A1: Task 3b · Stage the Rail file
A2: The two title rows were already removed for you (in Power BI you'd do it with Remove Top Rows). Fill the yellow columns.
A3: RAW — copied exactly as received (grey, don't edit) | H3: STAGED — contract columns (your formulas in yellow)
A4: Consignment No | B4: Dispatch Date | C4: From Station | D4: To Station | E4: Weight (Tons) | F4: Freight Charges (PKR) | G4: Status | H4: ShipmentID | I4: ShipDate | J4: Origin | K4: Destination | L4: WeightKG | M4: CostPKR | N4: Status | O4: SourceSystem | R4: Hints
A5: 45012 | B5: 46056 | C5: Karachi Cantt | D5: Lahore | E5: 32.5 | F5: 285000 | G5: Delivered | H5: ="RL-" & A5 -> RL-45012 | I5: =B5 -> 46056 | J5: =C5 -> Karachi Cantt | K5: =D5 -> Lahore | L5: =E5 * 1000 -> 32500 | M5: =F5 -> 285000 | N5: =PROPER(TRIM(G5)) -> Delivered | O5: ="Rail" -> Rail | R5: ShipmentID: join the text 'RL-' to the number with & → RL-45012.
A6: 45013 | B6: 46056 | C6: Karachi Cantt | D6: Rawalpindi | E6: 28.75 | F6: 301000 | G6: delivered | H6: ="RL-" & A6 -> RL-45013 | I6: =B6 -> 46056 | J6: =C6 -> Karachi Cantt | K6: =D6 -> Rawalpindi | L6: =E6 * 1000 -> 28750 | M6: =F6 -> 301000 | N6: =PROPER(TRIM(G6)) -> Delivered | O6: ="Rail" -> Rail | R6: WeightKG: Rail is in TONNES. 1 tonne = 1,000 kg.
A7: 45014 | B7: 46057 | C7: Pipri Marshalling Yard | D7: Faisalabad | E7: 30 | F7: 262000 | G7: In transit | H7: ="RL-" & A7 -> RL-45014 | I7: =B7 -> 46057 | J7: =C7 -> Pipri Marshalling Yard | K7: =D7 -> Faisalabad | L7: =E7 * 1000 -> 30000 | M7: =F7 -> 262000 | N7: =PROPER(TRIM(G7)) -> In Transit | O7: ="Rail" -> Rail | R7: Status: same trick as Marine.
A8: 45015 | B8: 46058 | C8: Karachi Cantt | D8: Multan | E8: 26.5 | F8: 198000 | G8: Delivered | H8: ="RL-" & A8 -> RL-45015 | I8: =B8 -> 46058 | J8: =C8 -> Karachi Cantt | K8: =D8 -> Multan | L8: =E8 * 1000 -> 26500 | M8: =F8 -> 198000 | N8: =PROPER(TRIM(G8)) -> Delivered | O8: ="Rail" -> Rail | R8: Check: RL-45012 should weigh 32,500 kg.
A9: 45016 | B9: 46059 | C9: Pipri Marshalling Yard | D9: Lahore | E9: 31.25 | F9: 276000 | G9: DELAYED | H9: ="RL-" & A9 -> RL-45016 | I9: =B9 -> 46059 | J9: =C9 -> Pipri Marshalling Yard | K9: =D9 -> Lahore | L9: =E9 * 1000 -> 31250 | M9: =F9 -> 276000 | N9: =PROPER(TRIM(G9)) -> Delayed | O9: ="Rail" -> Rail
A10: 45017 | B10: 46060 | C10: Karachi Cantt | D10: Peshawar Cantt | E10: 29 | F10: 334000 | G10: Delivered | H10: ="RL-" & A10 -> RL-45017 | I10: =B10 -> 46060 | J10: =C10 -> Karachi Cantt | K10: =D10 -> Peshawar Cantt | L10: =E10 * 1000 -> 29000 | M10: =F10 -> 334000 | N10: =PROPER(TRIM(G10)) -> Delivered | O10: ="Rail" -> Rail
A11: 45018 | B11: 46062 | C11: Pipri Marshalling Yard | D11: Rawalpindi | E11: 27.5 | F11: 289000 | G11: delayed | H11: ="RL-" & A11 -> RL-45018 | I11: =B11 -> 46062 | J11: =C11 -> Pipri Marshalling Yard | K11: =D11 -> Rawalpindi | L11: =E11 * 1000 -> 27500 | M11: =F11 -> 289000 | N11: =PROPER(TRIM(G11)) -> Delayed | O11: ="Rail" -> Rail
A12: 45019 | B12: 46063 | C12: Karachi Cantt | D12: Lahore | E12: 33 | F12: 291000 | G12: Delivered | H12: ="RL-" & A12 -> RL-45019 | I12: =B12 -> 46063 | J12: =C12 -> Karachi Cantt | K12: =D12 -> Lahore | L12: =E12 * 1000 -> 33000 | M12: =F12 -> 291000 | N12: =PROPER(TRIM(G12)) -> Delivered | O12: ="Rail" -> Rail
A13: 45020 | B13: 46064 | C13: Karachi Cantt | D13: Sukkur | E13: 28.25 | F13: 142000 | G13: in Transit | H13: ="RL-" & A13 -> RL-45020 | I13: =B13 -> 46064 | J13: =C13 -> Karachi Cantt | K13: =D13 -> Sukkur | L13: =E13 * 1000 -> 28250 | M13: =F13 -> 142000 | N13: =PROPER(TRIM(G13)) -> In Transit | O13: ="Rail" -> Rail
A14: 45021 | B14: 46065 | C14: Pipri Marshalling Yard | D14: Multan | E14: 28.5 | F14: 207000 | G14: delivered | H14: ="RL-" & A14 -> RL-45021 | I14: =B14 -> 46065 | J14: =C14 -> Pipri Marshalling Yard | K14: =D14 -> Multan | L14: =E14 * 1000 -> 28500 | M14: =F14 -> 207000 | N14: =PROPER(TRIM(G14)) -> Delivered | O14: ="Rail" -> Rail

Sheet T3c Road_Stg
A1: Task 3c · Stage the Road file
A2: Road has junk rows. Transform every row, then decide in 'Keep?' which rows are real shipments (Y) and which must be removed (N) — with a reason.
A3: RAW — copied exactly as received (grey, don't edit) | H3: STAGED — contract columns (your formulas in yellow)
A4: trip_id | B4: trip_date | C4: from_city | D4: to_city | E4: weight_kg | F4: cost_pkr | G4: status | H4: ShipmentID | I4: ShipDate | J4: Origin | K4: Destination | L4: WeightKG | M4: CostPKR | N4: Status | O4: SourceSystem | P4: Keep? (Y/N) | Q4: Reason if N | R4: Hints
A5: rd-501 | B5: 2026-02-02 | C5: Lahore | D5: Islamabad | E5: 6500 | F5: 58000 | G5: delivered | H5: =UPPER(A5) -> RD-501 | I5: =DATE(LEFT(B5,4), MID(B5,6,2), RIGHT(B5,2)) -> 46055 | J5: =IF(C5="","",C5) -> Lahore | K5: =IF(D5="","",D5) -> Islamabad | L5: =IF(E5="","",E5) -> 6500 | M5: =IF(F5="","",F5) -> 58000 | N5: =PROPER(TRIM(G5)) -> Delivered | O5: Road | P5: Y | R5: ShipmentID: make it UPPERCASE → RD-501.
A6: rd-502 | B6: 2026-02-02 | C6: Karachi | D6: Hyderabad | E6: 7200 | F6: 41000 | G6: delivered | H6: =UPPER(A6) -> RD-502 | I6: =DATE(LEFT(B6,4), MID(B6,6,2), RIGHT(B6,2)) -> 46055 | J6: =IF(C6="","",C6) -> Karachi | K6: =IF(D6="","",D6) -> Hyderabad | L6: =IF(E6="","",E6) -> 7200 | M6: =IF(F6="","",F6) -> 41000 | N6: =PROPER(TRIM(G6)) -> Delivered | O6: Road | P6: Y | R6: ShipDate: B is text like 2026-02-02. DATEVALUE turns it into a date; wrap it in IFERROR for the junk rows.
A7: rd-503 | B7: 2026-02-03 | C7: Lahore | D7: Faisalabad | E7: 5800 | F7: 32000 | G7: in transit | H7: =UPPER(A7) -> RD-503 | I7: =DATE(LEFT(B7,4), MID(B7,6,2), RIGHT(B7,2)) -> 46056 | J7: =IF(C7="","",C7) -> Lahore | K7: =IF(D7="","",D7) -> Faisalabad | L7: =IF(E7="","",E7) -> 5800 | M7: =IF(F7="","",F7) -> 32000 | N7: =PROPER(TRIM(G7)) -> In Transit | O7: Road | P7: Y | R7: Keep?: there are 15 raw lines but only 12 real trips. Find the 3 that must go.
A8: rd-504 | B8: 2026-02-04 | C8: Multan | D8: Lahore | E8: 6900 | F8: 61000 | G8: delivered | H8: =UPPER(A8) -> RD-504 | I8: =DATE(LEFT(B8,4), MID(B8,6,2), RIGHT(B8,2)) -> 46057 | J8: =IF(C8="","",C8) -> Multan | K8: =IF(D8="","",D8) -> Lahore | L8: =IF(E8="","",E8) -> 6900 | M8: =IF(F8="","",F8) -> 61000 | N8: =PROPER(TRIM(G8)) -> Delivered | O8: Road | P8: Y | R8: Status: TRIM + PROPER again.
A9: rd-505 | B9: 2026-02-05 | C9: Islamabad | D9: Peshawar | E9: 6100 | F9: 47000 | G9: delivered | H9: =UPPER(A9) -> RD-505 | I9: =DATE(LEFT(B9,4), MID(B9,6,2), RIGHT(B9,2)) -> 46058 | J9: =IF(C9="","",C9) -> Islamabad | K9: =IF(D9="","",D9) -> Peshawar | L9: =IF(E9="","",E9) -> 6100 | M9: =IF(F9="","",F9) -> 47000 | N9: =PROPER(TRIM(G9)) -> Delivered | O9: Road | P9: Y | R9: Why not just delete the junk rows? Because staging keeps the raw copy — you mark and explain, so the audit trail survives.
A10: rd-505 | B10: 2026-02-05 | C10: Islamabad | D10: Peshawar | E10: 6100 | F10: 47000 | G10: delivered | H10: =UPPER(A10) -> RD-505 | I10: =DATE(LEFT(B10,4), MID(B10,6,2), RIGHT(B10,2)) -> 46058 | J10: =IF(C10="","",C10) -> Islamabad | K10: =IF(D10="","",D10) -> Peshawar | L10: =IF(E10="","",E10) -> 6100 | M10: =IF(F10="","",F10) -> 47000 | N10: =PROPER(TRIM(G10)) -> Delivered | O10: Road | P10: N | Q10: Duplicate record — causes double-counting of weight and cost.
A11: rd-506 | B11: 2026-02-06 | C11: Karachi | D11: Sukkur | E11: 7400 | F11: 83000 | G11: delayed | H11: =UPPER(A11) -> RD-506 | I11: =DATE(LEFT(B11,4), MID(B11,6,2), RIGHT(B11,2)) -> 46059 | J11: =IF(C11="","",C11) -> Karachi | K11: =IF(D11="","",D11) -> Sukkur | L11: =IF(E11="","",E11) -> 7400 | M11: =IF(F11="","",F11) -> 83000 | N11: =PROPER(TRIM(G11)) -> Delayed | O11: Road | P11: Y
A12: rd-507 | B12: 2026-02-07 | C12: Lahore | D12: Sialkot | E12: 5900 | F12: 39000 | G12: delivered | H12: =UPPER(A12) -> RD-507 | I12: =DATE(LEFT(B12,4), MID(B12,6,2), RIGHT(B12,2)) -> 46060 | J12: =IF(C12="","",C12) -> Lahore | K12: =IF(D12="","",D12) -> Sialkot | L12: =IF(E12="","",E12) -> 5900 | M12: =IF(F12="","",F12) -> 39000 | N12: =PROPER(TRIM(G12)) -> Delivered | O12: Road | P12: Y
A13: rd-508 | B13: 2026-02-09 | C13: Quetta | D13: Karachi | E13: 6600 | F13: 92000 | G13: in transit | H13: =UPPER(A13) -> RD-508 | I13: =DATE(LEFT(B13,4), MID(B13,6,2), RIGHT(B13,2)) -> 46062 | J13: =IF(C13="","",C13) -> Quetta | K13: =IF(D13="","",D13) -> Karachi | L13: =IF(E13="","",E13) -> 6600 | M13: =IF(F13="","",F13) -> 92000 | N13: =PROPER(TRIM(G13)) -> In Transit | O13: Road | P13: Y
A14: rd-509 | B14: 2026-02-10 | C14: Faisalabad | D14: Multan | E14: 6200 | F14: 44000 | G14: delivered | H14: =UPPER(A14) -> RD-509 | I14: =DATE(LEFT(B14,4), MID(B14,6,2), RIGHT(B14,2)) -> 46063 | J14: =IF(C14="","",C14) -> Faisalabad | K14: =IF(D14="","",D14) -> Multan | L14: =IF(E14="","",E14) -> 6200 | M14: =IF(F14="","",F14) -> 44000 | N14: =PROPER(TRIM(G14)) -> Delivered | O14: Road | P14: Y
A15: rd-510 | B15: 2026-02-11 | C15: Lahore | D15: Gujranwala | E15: 7000 | F15: 27000 | G15: delivered | H15: =UPPER(A15) -> RD-510 | I15: =DATE(LEFT(B15,4), MID(B15,6,2), RIGHT(B15,2)) -> 46064 | J15: =IF(C15="","",C15) -> Lahore | K15: =IF(D15="","",D15) -> Gujranwala | L15: =IF(E15="","",E15) -> 7000 | M15: =IF(F15="","",F15) -> 27000 | N15: =PROPER(TRIM(G15)) -> Delivered | O15: Road | P15: Y
A16: rd-511 | B16: 2026-02-12 | C16: Karachi | D16: Hyderabad | E16: 5500 | F16: 36000 | G16: in transit | H16: =UPPER(A16) -> RD-511 | I16: =DATE(LEFT(B16,4), MID(B16,6,2), RIGHT(B16,2)) -> 46065 | J16: =IF(C16="","",C16) -> Karachi | K16: =IF(D16="","",D16) -> Hyderabad | L16: =IF(E16="","",E16) -> 5500 | M16: =IF(F16="","",F16) -> 36000 | N16: =PROPER(TRIM(G16)) -> In Transit | O16: Road | P16: Y
A17: rd-512 | B17: 2026-02-13 | C17: Rawalpindi | D17: Abbottabad | E17: 5800 | F17: 45000 | G17: delivered | H17: =UPPER(A17) -> RD-512 | I17: =DATE(LEFT(B17,4), MID(B17,6,2), RIGHT(B17,2)) -> 46066 | J17: =IF(C17="","",C17) -> Rawalpindi | K17: =IF(D17="","",D17) -> Abbottabad | L17: =IF(E17="","",E17) -> 5800 | M17: =IF(F17="","",F17) -> 45000 | N17: =PROPER(TRIM(G17)) -> Delivered | O17: Road | P17: Y
J18: =IF(C18="","",C18) | K18: =IF(D18="","",D18) | L18: =IF(E18="","",E18) | M18: =IF(F18="","",F18) | N18: =PROPER(TRIM(G18)) | P18: N | Q18: Empty non-data row — causes null errors in BI reports
A19: TOTAL | E19: 83000 | F19: 652000 | J19: =IF(C19="","",C19) | K19: =IF(D19="","",D19) | L19: =IF(E19="","",E19) -> 83000 | M19: =IF(F19="","",F19) -> 652000 | N19: =PROPER(TRIM(G19)) | O19: Road | P19: N | Q19: Summary row — causes double-counting of the entire dataset.

Sheet T4 Reconcile
A1: Task 4 · Reconcile — Validate Before You Trust (3 min)
A2: Nothing to type here. These checks read your staging tabs. Every ✘ means a mistake in Task 3 — go back and fix it until everything is ✔.
A4: Source | B4: Raw lines | C4: Removed | D4: Loaded | E4: Expected rows | F4: Weight (kg) | G4: Expected kg | H4: Check
A5: Marine | B5: =ROWS('T3a Marine_Stg'!A5:A16) -> 12 | C5: =0 -> 0 | D5: =COUNT('T3a Marine_Stg'!L5:L16) -> 12 | E5: 12 | F5: =SUM('T3a Marine_Stg'!L5:L16) -> 206500 | G5: 206500 | H5: =IF(AND(D5=E5,ABS(F5-G5)<0.5),"✔ OK","✘ Fix it") -> ✔ OK
A6: Rail | B6: =ROWS('T3b Rail_Stg'!A5:A14) -> 10 | C6: =0 -> 0 | D6: =COUNT('T3b Rail_Stg'!L5:L14) -> 10 | E6: 10 | F6: =SUM('T3b Rail_Stg'!L5:L14) -> 295250 | G6: 295250 | H6: =IF(AND(D6=E6,ABS(F6-G6)<0.5),"✔ OK","✘ Fix it") -> ✔ OK
A7: Road | B7: =ROWS('T3c Road_Stg'!A5:A19) -> 15 | C7: =COUNTIF('T3c Road_Stg'!P5:P19,"N") -> 3 | D7: =COUNTIF('T3c Road_Stg'!P5:P19,"Y") -> 12 | E7: 12 | F7: =SUMIF('T3c Road_Stg'!P5:P19,"Y",'T3c Road_Stg'!L5:L19) -> 76900 | G7: 76900 | H7: =IF(AND(D7=E7,ABS(F7-G7)<0.5),"✔ OK","✘ Fix it") -> ✔ OK
A8: Total | B8: =SUM(B5:B7) -> 37 | C8: =SUM(C5:C7) -> 3 | D8: =SUM(D5:D7) -> 34 | E8: =SUM(E5:E7) -> 34 | F8: =SUM(F5:F7) -> 578650 | G8: =SUM(G5:G7) -> 578650 | H8: =IF(AND(D8=34,ABS(F8-578650)<0.5,B8-C8=D8),"✔ OK","✘ Fix it") -> ✔ OK
A10: Total freight (tonnes) | F10: =F8/1000 -> 578.65 | G10: 578.65 | H10: =IF(ABS(F10-G10)<0.001,"✔ OK","✘ Fix it") -> ✔ OK
A11: Reconciliation rule: Raw lines − Removed = Loaded. Every removed row must have a reason in T3c.
A12: Expected values (blue) are the official lab answers from slide 39.
A14: Status | B14: Marine | C14: Rail | D14: Road (kept) | E14: Total | F14: Expected | H14: Check
A15: Delivered | B15: =COUNTIF('T3a Marine_Stg'!N5:N16,A15) -> 8 | C15: =COUNTIF('T3b Rail_Stg'!N5:N14,A15) -> 6 | D15: =COUNTIFS('T3c Road_Stg'!N5:N19,A15,'T3c Road_Stg'!P5:P19,"Y") -> 8 | E15: =SUM(B15:D15) -> 22 | F15: 22 | H15: =IF(E15=F15,"✔ OK","✘ Fix it") -> ✔ OK
A16: In Transit | B16: =COUNTIF('T3a Marine_Stg'!N5:N16,A16) -> 3 | C16: =COUNTIF('T3b Rail_Stg'!N5:N14,A16) -> 2 | D16: =COUNTIFS('T3c Road_Stg'!N5:N19,A16,'T3c Road_Stg'!P5:P19,"Y") -> 3 | E16: =SUM(B16:D16) -> 8 | F16: 8 | H16: =IF(E16=F16,"✔ OK","✘ Fix it") -> ✔ OK
A17: Delayed | B17: =COUNTIF('T3a Marine_Stg'!N5:N16,A17) -> 1 | C17: =COUNTIF('T3b Rail_Stg'!N5:N14,A17) -> 2 | D17: =COUNTIFS('T3c Road_Stg'!N5:N19,A17,'T3c Road_Stg'!P5:P19,"Y") -> 1 | E17: =SUM(B17:D17) -> 4 | F17: 4 | H17: =IF(E17=F17,"✔ OK","✘ Fix it") -> ✔ OK
A18: Other status values | E18: =COUNTIF('T3a Marine_Stg'!N5:N16,"?*")+COUNTIF('T3b Rail_Stg'!N5:N14,"?*")+COUNTIFS('T3c Road_Stg'!N5:N19,"?*",'T3c Road_Stg'!P5:P19,"Y")-SUM(E15:E17) -> 0 | F18: 0 | H18: =IF(AND(E18=0,E15+E16+E17=34),"✔ OK","✘ Fix it") -> ✔ OK
A20: Date trap | B20: MR-1003 date | F20: ='T3a Marine_Stg'!I7 -> 46056 | G20: =DATE(2026,2,3) -> 46056 | H20: =IF(F20=G20,"✔ OK","✘ Fix it") -> ✔ OK
B21: MR-1012 date | F21: ='T3a Marine_Stg'!I16 -> 46066 | G21: =DATE(2026,2,13) -> 46066 | H21: =IF(F21=G21,"✔ OK","✘ Fix it") -> ✔ OK

Sheet T5 Lineage
A1: Task 5 · Trace the Lineage of One Number (5 min)
A2: Metric: Total Freight = 578.65 tonnes (the card on the CEO dashboard). Fill each tier from the SOURCE down to the REPORT. Model answer idea: slide 29.
A4: Tier | B4: What the data looks like here | C4: What changes here (transformation) | D4: Quality check you'd place here ✓ | E4: Audit / lineage info you'd keep
A5: 1 · Source files | B5: 3 separate files (Marine: 12 rows in kg; Rail: 10 rows in tons with title headers; Road: 15 rows with duplicates, blanks, and TOTAL row) | C5: None (Raw source files read directly as-is) | D5: Row count check per source file and file existence verification | E5: Source filename, file path, file size, landing timestamp, and raw row counts
A6: 2 · Staging | B6: Standardized schema (34 valid rows total; Rail converted to kg; 3 bad Road rows removed) | C6: Skip top 2 title rows in Rail; multiply Rail weight by 1,000; drop Road duplicate (rd-505), blank, and TOTAL row; trim and standardize casing and dates | D6: Reconciliation check: Ensure Loaded records = 34 (12+10+12) and Total weight = 578,650 kg | E6: Pipeline batch ID, execution start/end time, number of dropped/rejected rows, and transformation logs
A7: 3 · Storage (integrated) | B7: Single unified fact table (FactShipments) joined to conformed dimensions (DimDate, DimTransportMode, DimLocation) | C7: Assign surrogate keys, map raw locations to conformed dimension keys, and append modal flag (Marine/Rail/Road) | D7: Primary key uniqueness check (Shipment_Key), foreign key referential integrity checks | E7: Inserted timestamp, source system lineage ID, and data warehouse record load status
A8: 4 · Presentation | B8: Star-schema semantic model / Power BI dataset with an explicit DAX aggregate measure | C8: Create explicit total measure: Total Weight KG = SUM(FactShipments[Weight_KG]) (578,650 kg) | D8: Compare DAX measure result against staging total check (578,650 kg) | E8: Semantic model version, last refresh timestamp, and DAX measure definition
A9: 5 · Report | B9: Visual KPI Card on the CEO Dashboard displaying 578.65 t | C9: Format weight in metric tonnes by dividing Total Weight KG by 1,000 or applying Power BI visual unit display formatting (/ 1000) | D9: Visual threshold check (> 0 and within expected operational limits) | E9: Dashboard refresh timestamp, report user view logs, and visual query definition
A11: Where do tonnes become kilograms — and why there and not in the dashboard?
A12: Tonnes become kilograms in the Staging tier (Tier 2). We convert units in staging so all records are stored in a single standardized base unit kg inside the database. If unit conversion were left to the dashboard, different report builders might forget to convert or use different formulas, leading to inconsistent numbers across reports.

Sheet T6 Bus Matrix
A1: Task 6 · Kimball Bus Matrix (7 min)
A2: Rows = PakFreight business processes (each becomes one star schema). Columns = dimensions. Put X where a process needs that dimension. Dimensions used by many processes must be CONFORMED (built once, shared by all stars) — that is what stops stovepipes.
A4: Business process (fact table) | B4: Date | C4: Customer | D4: Route | E4: Vehicle | F4: Driver | G4: Station / Port | H4: Commodity | I4: Dims used
A5: Shipments | B5: X | C5: X | D5: X | E5: X | G5: X | H5: X | I5: 6
A6: Billing & Invoicing | B6: X | C6: X | D6: X | H6: X | I6: 4
A7: Fleet Maintenance | B7: X | E7: X | I7: 2
A8: Fuel Purchases | B8: X | E8: X | F8: X | G8: X | I8: 4
A9: Driver Trips & Hours | B9: X | D9: X | E9: X | F9: X | G9: X | I9: 5
A10: Customer Complaints | B10: X | C10: X | I10: 2
A11: Processes using this dim | B11: 6 | C11: 3 | D11: 3 | E11: 4 | F11: 2 | G11: 3 | H11: 2
A12: Row 1 (Shipments) is filled as an example.
A14: Q1. Which dimension is used by EVERY process? Why is it always conformed first?
A15: The Date dimension. It is always conformed first because every business process occurs over time, making a single shared Date table essential for cross-process trend analysis, performance comparison, and financial reporting
A16: Q2. Which 2–3 dimensions must Finance, Ops and Sales agree on to stop the '3 different totals' problem?
A17: Date, Route (or Station/Port), and Commodity. Standardizing these dimensions ensures all three departments aggregate shipments using identical time boundaries, origin/destination mappings, and cargo classifications
A18: Q3. Kimball is 'bottom-up'. Does that mean he doesn't plan? What does this matrix prove?
A19: No, Kimball plans extensively through the Bus Matrix. The matrix proves that bottom-up design is architected in advance by mapping conformed dimensions across business processes so datasets can be built incrementally without creating isolated data silos.
A20: Q4. Which row would you build first for the COO, and why?
A21: It is the primary core operational process that uses the most dimensions 6, directly generating revenue and operational activity that feeds downstream processes like Billing and Driver Trips.

Sheet T7 Inmon or Kimball
A1: Task 7 · Inmon, Kimball or Hybrid? (5 min)
A2: Pick from the drop-down for each statement and give a one-line reason. Your teacher will reveal the answers.
A4: # | B4: Statement / scenario | C4: Inmon · Kimball · Hybrid | D4: Why? (one line)
A5: 1 | B5: A bank must integrate 40 systems into one enterprise model for regulators before anyone builds reports. | C5: Inmon | D5: Inmon prioritizes a top-down, centralized 3NF enterprise warehouse to meet strict, single-source regulatory requirements first.
A6: 2 | B6: PakFreight's COO wants a useful shipments dashboard within 3 months. | C6: Kimball | D6: Kimball uses a bottom-up dimensional approach that delivers fast, iterative value business process by business process.
A7: 3 | B7: The core warehouse is stored in normalised third normal form (3NF). | C7: Inmon | D7: Inmon relies on a centralized 3NF relational model to minimize data redundancy and maintain atomicity.
A8: 4 | B8: Data marts ARE the presentation area, tied together by conformed dimensions. | C8: Kimball | D8: Kimball builds the enterprise warehouse directly out of dimensional data marts linked by shared (conformed) dimensions.
A9: 5 | B9: The bus matrix is planned for the whole company, but built one process at a time. | C9: Kimball | D9: The Kimball Bus Architecture acts as the strategic roadmap for incrementally building conformed dimensional models.
A10: 6 | B10: Departments get dependent marts that are derived from the central EDW. | C10: Inmon | D10: Inmon feeds departmental data marts downstream from the single centralized 3NF Enterprise Data Warehouse.
A11: 7 | B11: Biggest risk: a long wait before users see any value. | C11: Inmon | D11: Building a comprehensive enterprise 3NF model upfront requires significant time before delivering reportable value.
A12: 8 | B12: Biggest risk: sliding back into stovepipes if teams ignore conformance. | C12: Kimball | D12: Without strict governance over conformed dimensions, independent Kimball marts deteriorate into isolated data silos.
A13: 9 | B13: Start from the data; users discover real requirements after they see it (CLDS). | C13: Inmon | D13: Inmon follows the Data-Driven (CLDS: Climate, Data, System, Result) life cycle, starting with data integration.
A14: 10 | B14: Bronze raw files → Silver cleaned & integrated tables → Gold star schemas in Microsoft Fabric. | C14: Hybrid | D14: The Medallion Architecture blends Inmon-style normalized storage (Silver) with Kimball-style dimensional reporting (Gold).
